[
  {
    "sent": "主 诉 ： 停 经 3 7 + 3 周 ， 阴 道 见 红 2 小 时",
    "ners": [
      [
        3,
        5,
        "clinicalFeature",
        "停经"
      ],
      [
        5,
        10,
        "time",
        "37+3周"
      ],
      [
        11,
        13,
        "body",
        "阴道"
      ],
      [
        11,
        15,
        "clinicalFeature",
        "阴道见红"
      ],
      [
        15,
        18,
        "time",
        "2小时"
      ]
    ],
    "sentence_text": "[CLS] 主 诉 ： 停 经 3 7 + 3 周 ， 阴 道 见 红 2 小 时 [SEP] [clinicalFeature] [/clinicalFeature] [time] [/time] [body] [/body] [clinicalFeature] [/clinicalFeature] [time] [/time]",
    "position_ids": [
      0,
      1,
      2,
      3,
      4,
      5,
      6,
      7,
      8,
      9,
      10,
      11,
      12,
      13,
      14,
      15,
      16,
      17,
      18,
      19,
      4,
      5,
      6,
      10,
      12,
      13,
      12,
      15,
      16,
      18
    ],
    "relation": [
      "[3, 5, 'clinicalFeature', '停经']\t[5, 10, 'time', '37+3周']",
      "[3, 5, 'clinicalFeature', '停经']\t[11, 13, 'body', '阴道']",
      "[3, 5, 'clinicalFeature', '停经']\t[11, 15, 'clinicalFeature', '阴道见红']",
      "[3, 5, 'clinicalFeature', '停经']\t[15, 18, 'time', '2小时']",
      "[5, 10, 'time', '37+3周']\t[3, 5, 'clinicalFeature', '停经']",
      "[5, 10, 'time', '37+3周']\t[11, 13, 'body', '阴道']",
      "[5, 10, 'time', '37+3周']\t[11, 15, 'clinicalFeature', '阴道见红']",
      "[5, 10, 'time', '37+3周']\t[15, 18, 'time', '2小时']",
      "[11, 13, 'body', '阴道']\t[3, 5, 'clinicalFeature', '停经']",
      "[11, 13, 'body', '阴道']\t[5, 10, 'time', '37+3周']",
      "[11, 13, 'body', '阴道']\t[11, 15, 'clinicalFeature', '阴道见红']",
      "[11, 13, 'body', '阴道']\t[15, 18, 'time', '2小时']",
      "[11, 15, 'clinicalFeature', '阴道见红']\t[3, 5, 'clinicalFeature', '停经']",
      "[11, 15, 'clinicalFeature', '阴道见红']\t[5, 10, 'time', '37+3周']",
      "[11, 15, 'clinicalFeature', '阴道见红']\t[11, 13, 'body', '阴道']",
      "[11, 15, 'clinicalFeature', '阴道见红']\t[15, 18, 'time', '2小时']",
      "[15, 18, 'time', '2小时']\t[3, 5, 'clinicalFeature', '停经']",
      "[15, 18, 'time', '2小时']\t[5, 10, 'time', '37+3周']",
      "[15, 18, 'time', '2小时']\t[11, 13, 'body', '阴道']",
      "[15, 18, 'time', '2小时']\t[11, 15, 'clinicalFeature', '阴道见红']"
    ],
    "relation_label": [
      "无",
      "无",
      "无",
      "无",
      "无",
      "无",
      "无",
      "无",
      "无",
      "无",
      "无",
      "无",
      "无",
      "无",
      "无",
      "无",
      "无",
      "无",
      "无",
      "无"
    ],
    "relation_idx": [
      [
        20,
        21,
        22,
        23
      ],
      [
        20,
        21,
        24,
        25
      ],
      [
        20,
        21,
        26,
        27
      ],
      [
        20,
        21,
        28,
        29
      ],
      [
        22,
        23,
        20,
        21
      ],
      [
        22,
        23,
        24,
        25
      ],
      [
        22,
        23,
        26,
        27
      ],
      [
        22,
        23,
        28,
        29
      ],
      [
        24,
        25,
        20,
        21
      ],
      [
        24,
        25,
        22,
        23
      ],
      [
        24,
        25,
        26,
        27
      ],
      [
        24,
        25,
        28,
        29
      ],
      [
        26,
        27,
        20,
        21
      ],
      [
        26,
        27,
        22,
        23
      ],
      [
        26,
        27,
        24,
        25
      ],
      [
        26,
        27,
        28,
        29
      ],
      [
        28,
        29,
        20,
        21
      ],
      [
        28,
        29,
        22,
        23
      ],
      [
        28,
        29,
        24,
        25
      ],
      [
        28,
        29,
        26,
        27
      ]
    ]
  }
]